<?xml version="1.0" encoding="utf-8"?>
<savedqueries xmlns:xsi="http://www.w3.org/2001/XMLSchema-instance">
  <savedquery>
    <IsCustomizable>1</IsCustomizable>
    <CanBeDeleted>0</CanBeDeleted>
    <isquickfindquery>0</isquickfindquery>
    <isprivate>0</isprivate>
    <isdefault>1</isdefault>
    <savedqueryid>{1994268b-5389-40eb-a6ee-a713c9f43177}</savedqueryid>
    <layoutxml>
      <grid name="rt_rooms" jump="rt_name" select="1" icon="1" preview="1">
        <row name="rt_room" id="rt_roomid">
          <cell name="rt_name" width="300" />
          <cell name="rt_location" width="100" />
          <cell name="rt_maxparticipants" width="136" />
          <cell name="rt_roomtype" width="106" />
          <cell name="rt_equipment" width="102" />
          <cell name="createdon" width="125" />
        </row>
      </grid>
    </layoutxml>
    <querytype>2</querytype>
    <fetchxml>
      <fetch version="1.0" mapping="logical">
        <entity name="rt_room">
          <attribute name="rt_roomid" />
          <attribute name="rt_name" />
          <attribute name="createdon" />
          <order attribute="rt_name" descending="false" />
          <filter type="and">
            <condition attribute="statecode" operator="eq" value="0" />
          </filter>
          <attribute name="rt_location" />
          <attribute name="rt_maxparticipants" />
          <attribute name="rt_equipment" />
          <attribute name="rt_roomtype" />
        </entity>
      </fetch>
    </fetchxml>
    <IntroducedVersion>1.0</IntroducedVersion>
    <LocalizedNames>
      <LocalizedName description="Gekoppelde weergave van Room" languagecode="1033" />
    </LocalizedNames>
  </savedquery>
</savedqueries>